meenpy/__init__.py
meenpy/numerics/__init__.py
meenpy/numerics/utils/__init__.py
meenpy-0.1.5.dist-info/WHEEL
meenpy-0.1.5.dist-info/METADATA
meenpy-0.1.5.dist-info/RECORD
