Metadata-Version: 2.3
Name: meenpy
Version: 0.1.5
Summary: meenpy is a library of utilities for mechanical engineering problem solving.
Author: Caleb Fowler
Author-email: Caleb Fowler <caleb.fowler.atx@gmail.com>
Requires-Dist: matplotlib>=3.10.6
Requires-Dist: numpy>=2.3.3
Requires-Dist: pandas>=2.3.2
Requires-Dist: plotly>=6.3.0
Requires-Dist: scipy>=1.16.2
Requires-Dist: sympy>=1.14.0
Requires-Python: >=3.12
